django_multilingual_model-0.6.dist-info/DESCRIPTION.rst
django_multilingual_model-0.6.dist-info/METADATA
django_multilingual_model-0.6.dist-info/metadata.json
django_multilingual_model-0.6.dist-info/RECORD
django_multilingual_model-0.6.dist-info/top_level.txt
django_multilingual_model-0.6.dist-info/WHEEL
multilingual_model/__init__.py
multilingual_model/admin.py
multilingual_model/forms.py
multilingual_model/models.py
multilingual_model/settings.py
multilingual_model/tests.py
