Metadata-Version: 2.0
Name: django-multilingual-model
Version: 0.6
Summary: Django Simple Multilingual Support for Models.
Home-page: http://github.com/dokterbob/django-multilingual-model
Author: Mathijs de Bruin
Author-email: mathijs@mathijsfietst.nl
License: UNKNOWN
Platform: UNKNOWN
Classifier: Development Status :: 3 - Alpha
Classifier: Environment :: Web Environment
Classifier: Framework :: Django
Classifier: Intended Audience :: Developers
Classifier: License :: OSI Approved :: GNU Affero General Public License v3
Classifier: Operating System :: OS Independent
Classifier: Programming Language :: Python
Classifier: Programming Language :: Python :: 2
Classifier: Programming Language :: Python :: 2.6
Classifier: Programming Language :: Python :: 2.7
Classifier: Programming Language :: Python :: 3
Classifier: Programming Language :: Python :: 3.3
